intreg_stats/__init__.py
intreg_stats/estimator.py
intreg_stats-0.1.1.dist-info/METADATA
intreg_stats-0.1.1.dist-info/WHEEL
intreg_stats-0.1.1.dist-info/top_level.txt
intreg_stats-0.1.1.dist-info/RECORD
