Metadata-Version: 2.4
Name: intreg_stats
Version: 0.1.1
Summary: MARINER + HIREG
Author: Aymen Echarghaoui
License: MIT
Keywords: lasso,unilasso,interactions,regression
Classifier: Programming Language :: Python :: 3
Classifier: License :: OSI Approved :: MIT License
Classifier: Intended Audience :: Science/Research
Classifier: Topic :: Scientific/Engineering
Requires-Python: >=3.9
